flask_management/__main__.py
flask_management/constants.py
flask_management/context.py
flask_management/main.py
flask_management/templates/__init__.py
flask_management/templates/project/__init__.py
flask_management/templates/project/cookiecutter.json
flask_management/templates/project/{{ cookiecutter.folder_name }}/.gitignore
flask_management/templates/project/{{ cookiecutter.folder_name }}/README.md
flask_management/templates/project/{{ cookiecutter.folder_name }}/pyproject.toml
flask_management/templates/project/{{ cookiecutter.folder_name }}/setup.cfg
flask_management/templates/project/{{ cookiecutter.folder_name }}/tests/__init__.py
flask_management/templates/project/{{ cookiecutter.folder_name }}/{{ cookiecutter.app_name }}/__init__.py
flask_management/templates/project/{{ cookiecutter.folder_name }}/{{ cookiecutter.app_name }}/app_settings.py
flask_management/templates/project/{{ cookiecutter.folder_name }}/{{ cookiecutter.app_name }}/book/__init__.py
flask_management/templates/project/{{ cookiecutter.folder_name }}/{{ cookiecutter.app_name }}/book/api.py
flask_management/templates/project/{{ cookiecutter.folder_name }}/{{ cookiecutter.app_name }}/ext.py
flask_management/templates/project/{{ cookiecutter.folder_name }}/{{ cookiecutter.app_name }}/models.py
flask_management/templates/project/{{ cookiecutter.folder_name }}/{{ cookiecutter.app_name }}/signals.py
flask_management/templates/project/{{ cookiecutter.folder_name }}/{{ cookiecutter.env }}
flask_management-0.1.5.dist-info/LICENSE
flask_management-0.1.5.dist-info/METADATA
flask_management-0.1.5.dist-info/WHEEL
flask_management-0.1.5.dist-info/entry_points.txt
flask_management-0.1.5.dist-info/RECORD
